{
"type": "FeatureCollection",
"crs": { "type": "name", "properties": { "name": "urn:ogc:def:crs:OGC:1.3:CRS84" } },
"features": [
{ "type": "Feature", "properties": { "point": "Waste Water Treatment Plant of Agadir", "type": "WWTP" }, "geometry": { "type": "Point", "coordinates": [ -9.58446, 30.26983 ] } },
{ "type": "Feature", "properties": { "point": "Waste Water Treatment Plant of Biougra", "type": "WWTP" }, "geometry": { "type": "Point", "coordinates": [ -9.33411, 30.13976 ] } },
{ "type": "Feature", "properties": { "point": "Waste Water Treatment Plant of Ouled Teima", "type": "WWTP" }, "geometry": { "type": "Point", "coordinates": [ -9.25989, 30.5224 ] } },
{ "type": "Feature", "properties": { "point": "Waste Water Treatment Plant of Tiznit", "type": "WWTP" }, "geometry": { "type": "Point", "coordinates": [ -9.96306, 29.6246 ] } }
]
}
